reachy_mini_toolbox/__init__.py
reachy_mini_toolbox/moves/recorder.py
reachy_mini_toolbox/vision/__init__.py
reachy_mini_toolbox/vision/hand_tracker.py
reachy_mini_toolbox/vision/head_tracker.py
reachy_mini_toolbox-1.1.2.dist-info/licenses/LICENSE
reachy_mini_toolbox-1.1.2.dist-info/METADATA
reachy_mini_toolbox-1.1.2.dist-info/WHEEL
reachy_mini_toolbox-1.1.2.dist-info/top_level.txt
reachy_mini_toolbox-1.1.2.dist-info/RECORD
